{
    "title": "Главная страница",
    "headerFixed": false,
    "headerDark": true,
    "script": true,
    "otherScript": true,
    "otherScriptTag": [
        "https://unpkg.com/panzoom@9.4.0/dist/panzoom.min.js",
        "https://cdnjs.cloudflare.com/ajax/libs/bootstrap-datepicker/1.10.0/js/bootstrap-datepicker.min.js",
        "https://cdn.jsdelivr.net/npm/dayjs@1/dayjs.min.js",
        "https://cdnjs.cloudflare.com/ajax/libs/bootstrap-datepicker/1.10.0/locales/bootstrap-datepicker.ru.min.js",
        "https://cdn.jsdelivr.net/npm/handlebars@latest/dist/handlebars.js",
        "./assets/js/booking/custom-calendar.js",
        "./assets/js/booking/main_copy.js"
    ]
}
